CHANGES.rst
DESCRIPTION.rst
LICENSE
MANIFEST.in
README.md
setup.py
src/idc/labelme/__init__.py
src/idc/labelme/class_lister.py
src/idc/labelme/reader/imgcls/__init__.py
src/idc/labelme/reader/imgcls/_labelme.py
src/idc/labelme/reader/objdet/__init__.py
src/idc/labelme/reader/objdet/_labelme.py
src/idc/labelme/writer/imgcls/__init__.py
src/idc/labelme/writer/imgcls/_labelme.py
src/idc/labelme/writer/objdet/__init__.py
src/idc/labelme/writer/objdet/_labelme.py
src/image_dataset_converter_labelme.egg-info/PKG-INFO
src/image_dataset_converter_labelme.egg-info/SOURCES.txt
src/image_dataset_converter_labelme.egg-info/dependency_links.txt
src/image_dataset_converter_labelme.egg-info/entry_points.txt
src/image_dataset_converter_labelme.egg-info/requires.txt
src/image_dataset_converter_labelme.egg-info/top_level.txt